__init__.py
pyexql/__init__.py
pyexql/__main__.py
pyexql/main.py
pyexql/run.py
pyexql/validate.py
pyexql-0.0.1.dist-info/METADATA
pyexql-0.0.1.dist-info/WHEEL
pyexql-0.0.1.dist-info/entry_points.txt
pyexql-0.0.1.dist-info/top_level.txt
pyexql-0.0.1.dist-info/RECORD
