Metadata-Version: 2.1
Name: pyexql
Version: 0.0.1
Summary: ExQL
Author-email: ExQL <exql@googlegroups.com>
Project-URL: Homepage, https://google.com
Keywords: exql
Classifier: License :: OSI Approved :: MIT License
Classifier: Programming Language :: Python
Classifier: Programming Language :: Python :: 3
Requires-Python: >=3.9
Requires-Dist: fastapi
Requires-Dist: python-dotenv
Requires-Dist: snowflake-connector-python (==2.7.12)
Requires-Dist: uvicorn[standard]
